{
  "symbol": "EURUSD",
  "payload_ts": "2025-11-30T02:05:29.482184Z",
  "payload_seq": 26,
  "schema": null,
  "price": null,
  "session": null,
  "structure": {
    "trend": "UP",
    "bias": "LONG",
    "range_state": "DEV_DOWN",
    "legs": [
      {
        "label": "LL",
        "from_time": "2025-11-28T17:02:00+00:00",
        "to_time": "2025-11-28T17:07:00+00:00",
        "from_price": 1.160005,
        "to_price": 1.15952
      },
      {
        "label": "LH",
        "from_time": "2025-11-28T17:07:00+00:00",
        "to_time": "2025-11-28T17:11:00+00:00",
        "from_price": 1.15952,
        "to_price": 1.15983
      },
      {
        "label": "LL",
        "from_time": "2025-11-28T17:11:00+00:00",
        "to_time": "2025-11-28T17:13:00+00:00",
        "from_price": 1.15983,
        "to_price": 1.159435
      },
      {
        "label": "HH",
        "from_time": "2025-11-28T17:13:00+00:00",
        "to_time": "2025-11-28T17:20:00+00:00",
        "from_price": 1.159435,
        "to_price": 1.1598600000000001
      },
      {
        "label": "HL",
        "from_time": "2025-11-28T17:20:00+00:00",
        "to_time": "2025-11-28T17:21:00+00:00",
        "from_price": 1.1598600000000001,
        "to_price": 1.15961
      },
      {
        "label": "HH",
        "from_time": "2025-11-28T17:21:00+00:00",
        "to_time": "2025-11-28T17:24:00+00:00",
        "from_price": 1.15961,
        "to_price": 1.159865
      },
      {
        "label": "LL",
        "from_time": "2025-11-28T17:24:00+00:00",
        "to_time": "2025-11-28T17:31:00+00:00",
        "from_price": 1.159865,
        "to_price": 1.15939
      },
      {
        "label": "HL",
        "from_time": "2025-11-28T17:31:00+00:00",
        "to_time": "2025-11-28T17:41:00+00:00",
        "from_price": 1.15939,
        "to_price": 1.15974
      },
      {
        "label": "HH",
        "from_time": "2025-11-28T17:41:00+00:00",
        "to_time": "2025-11-28T17:45:00+00:00",
        "from_price": 1.15974,
        "to_price": 1.160005
      },
      {
        "label": "HL",
        "from_time": "2025-11-28T17:45:00+00:00",
        "to_time": "2025-11-28T17:52:00+00:00",
        "from_price": 1.160005,
        "to_price": 1.15983
      },
      {
        "label": "HL",
        "from_time": "2025-11-28T17:52:00+00:00",
        "to_time": "2025-11-28T17:57:00+00:00",
        "from_price": 1.15983,
        "to_price": 1.16009
      },
      {
        "label": "HH",
        "from_time": "2025-11-28T17:57:00+00:00",
        "to_time": "2025-11-28T17:59:00+00:00",
        "from_price": 1.16009,
        "to_price": 1.160425
      }
    ],
    "swings": [
      {
        "kind": "LOW",
        "price": 1.15998,
        "time": "2025-11-28T16:03:00+00:00"
      },
      {
        "kind": "HIGH",
        "price": 1.160195,
        "time": "2025-11-28T16:06:00+00:00"
      },
      {
        "kind": "LOW",
        "price": 1.15988,
        "time": "2025-11-28T16:09:00+00:00"
      },
      {
        "kind": "HIGH",
        "price": 1.16044,
        "time": "2025-11-28T16:12:00+00:00"
      },
      {
        "kind": "LOW",
        "price": 1.1595550000000001,
        "time": "2025-11-28T16:19:00+00:00"
      },
      {
        "kind": "HIGH",
        "price": 1.159865,
        "time": "2025-11-28T16:22:00+00:00"
      },
      {
        "kind": "LOW",
        "price": 1.159535,
        "time": "2025-11-28T16:24:00+00:00"
      },
      {
        "kind": "LOW",
        "price": 1.159535,
        "time": "2025-11-28T16:25:00+00:00"
      },
      {
        "kind": "HIGH",
        "price": 1.159945,
        "time": "2025-11-28T16:29:00+00:00"
      },
      {
        "kind": "LOW",
        "price": 1.15938,
        "time": "2025-11-28T16:31:00+00:00"
      },
      {
        "kind": "HIGH",
        "price": 1.16032,
        "time": "2025-11-28T16:42:00+00:00"
      },
      {
        "kind": "LOW",
        "price": 1.16006,
        "time": "2025-11-28T16:44:00+00:00"
      },
      {
        "kind": "HIGH",
        "price": 1.1602999999999999,
        "time": "2025-11-28T16:46:00+00:00"
      },
      {
        "kind": "HIGH",
        "price": 1.1602999999999999,
        "time": "2025-11-28T16:49:00+00:00"
      },
      {
        "kind": "LOW",
        "price": 1.16019,
        "time": "2025-11-28T16:51:00+00:00"
      },
      {
        "kind": "HIGH",
        "price": 1.16035,
        "time": "2025-11-28T16:53:00+00:00"
      },
      {
        "kind": "LOW",
        "price": 1.15974,
        "time": "2025-11-28T16:57:00+00:00"
      },
      {
        "kind": "HIGH",
        "price": 1.160005,
        "time": "2025-11-28T17:02:00+00:00"
      },
      {
        "kind": "LOW",
        "price": 1.15952,
        "time": "2025-11-28T17:07:00+00:00"
      },
      {
        "kind": "HIGH",
        "price": 1.15983,
        "time": "2025-11-28T17:11:00+00:00"
      },
      {
        "kind": "LOW",
        "price": 1.159435,
        "time": "2025-11-28T17:13:00+00:00"
      },
      {
        "kind": "HIGH",
        "price": 1.1598600000000001,
        "time": "2025-11-28T17:20:00+00:00"
      },
      {
        "kind": "LOW",
        "price": 1.15961,
        "time": "2025-11-28T17:21:00+00:00"
      },
      {
        "kind": "HIGH",
        "price": 1.159865,
        "time": "2025-11-28T17:24:00+00:00"
      },
      {
        "kind": "LOW",
        "price": 1.15939,
        "time": "2025-11-28T17:31:00+00:00"
      },
      {
        "kind": "LOW",
        "price": 1.15974,
        "time": "2025-11-28T17:41:00+00:00"
      },
      {
        "kind": "HIGH",
        "price": 1.160005,
        "time": "2025-11-28T17:45:00+00:00"
      },
      {
        "kind": "LOW",
        "price": 1.15983,
        "time": "2025-11-28T17:52:00+00:00"
      },
      {
        "kind": "LOW",
        "price": 1.16009,
        "time": "2025-11-28T17:57:00+00:00"
      },
      {
        "kind": "HIGH",
        "price": 1.160425,
        "time": "2025-11-28T17:59:00+00:00"
      }
    ],
    "ranges": [
      {
        "high": 1.160245,
        "low": 1.1596600000000001,
        "state": "DEV_DOWN",
        "start": "2025-11-28T18:01:00+00:00",
        "end": "2025-11-28T18:12:00+00:00"
      }
    ],
    "events": [],
    "ote_zones": []
  },
  "liquidity": {
    "amd_phase": "MANIPULATION",
    "pools": [
      {
        "level": 1.1590340625,
        "liq_type": "EQH",
        "role": "COUNTERTREND",
        "strength": 96.0
      },
      {
        "level": 1.1585730303030302,
        "liq_type": "EQL",
        "role": "PRIMARY",
        "strength": 99.0
      },
      {
        "level": 1.16009,
        "liq_type": "TLQ",
        "role": "PRIMARY",
        "strength": 3.0
      },
      {
        "level": 1.1596600000000001,
        "liq_type": "RANGE_EXTREME",
        "role": "PRIMARY",
        "strength": 0.0005849999999998357
      },
      {
        "level": 1.160245,
        "liq_type": "RANGE_EXTREME",
        "role": "COUNTERTREND",
        "strength": 0.0005849999999998357
      },
      {
        "level": 1.15651,
        "liq_type": "WICK_CLUSTER",
        "role": "PRIMARY",
        "strength": 7.00000000000145e-05
      },
      {
        "level": 1.156865,
        "liq_type": "WICK_CLUSTER",
        "role": "COUNTERTREND",
        "strength": 0.00012499999999993072
      },
      {
        "level": 1.156615,
        "liq_type": "WICK_CLUSTER",
        "role": "PRIMARY",
        "strength": 7.00000000000145e-05
      }
    ],
    "magnets": [
      {
        "price_min": 1.15651,
        "price_max": 1.16075,
        "role": "PRIMARY"
      }
    ]
  },
  "zones": {
    "raw": {
      "zones": [
        {
          "zone_type": "ORDER_BLOCK",
          "price_min": 1.156815,
          "price_max": 1.156855,
          "timeframe": "1m",
          "origin_time": "1970-01-01T00:29:24.336120",
          "direction": "LONG",
          "role": "NEUTRAL",
          "strength": 2.4390243902457214,
          "confidence": 0.6318181818186406,
          "components": [
            "orderblock",
            "leg_9_10"
          ],
          "zone_id": "ob_eurusd_1m_9_10",
          "entry_mode": "BODY_05",
          "quality": "WEAK",
          "reference_leg_id": "leg_9_10",
          "reference_event_id": null,
          "bias_at_creation": "LONG",
          "notes": "",
          "meta": {
            "body_pct": 0.7272727272745624,
            "wick_top_pct": 0.18181818181964987,
            "wick_bottom_pct": 0.09090909090578776,
            "entry_mode": "BODY_05",
            "role": "NEUTRAL",
            "bias_at_creation": "LONG",
            "has_bos": false,
            "bar_count": 2,
            "amplitude": 0.0002500000000000835,
            "quality": "WEAK"
          }
        },
        {
          "zone_type": "ORDER_BLOCK",
          "price_min": 1.156815,
          "price_max": 1.156855,
          "timeframe": "1m",
          "origin_time": "1970-01-01T00:29:24.336120",
          "direction": "LONG",
          "role": "NEUTRAL",
          "strength": 3.0,
          "confidence": 0.6318181818186406,
          "components": [
            "orderblock",
            "leg_10_17"
          ],
          "zone_id": "ob_eurusd_1m_9_17",
          "entry_mode": "BODY_05",
          "quality": "WEAK",
          "reference_leg_id": "leg_10_17",
          "reference_event_id": null,
          "bias_at_creation": "LONG",
          "notes": "",
          "meta": {
            "body_pct": 0.7272727272745624,
            "wick_top_pct": 0.18181818181964987,
            "wick_bottom_pct": 0.09090909090578776,
            "entry_mode": "BODY_05",
            "role": "NEUTRAL",
            "bias_at_creation": "LONG",
            "has_bos": false,
            "bar_count": 8,
            "amplitude": 0.0005699999999999594,
            "quality": "WEAK"
          }
        },
        {
          "zone_type": "ORDER_BLOCK",
          "price_min": 1.15692,
          "price_max": 1.156935,
          "timeframe": "1m",
          "origin_time": "1970-01-01T00:29:24.336540",
          "direction": "LONG",
          "role": "NEUTRAL",
          "strength": 3.0,
          "confidence": 0.5333333333333333,
          "components": [
            "orderblock",
            "leg_17_19"
          ],
          "zone_id": "ob_eurusd_1m_16_19",
          "entry_mode": "WICK_05",
          "quality": "WEAK",
          "reference_leg_id": "leg_17_19",
          "reference_event_id": null,
          "bias_at_creation": "LONG",
          "notes": "",
          "meta": {
            "body_pct": 0.3333333333333333,
            "wick_top_pct": 0.0,
            "wick_bottom_pct": 0.6666666666666666,
            "entry_mode": "WICK_05",
            "role": "NEUTRAL",
            "bias_at_creation": "LONG",
            "has_bos": false,
            "bar_count": 3,
            "amplitude": 0.0003249999999999087,
            "quality": "WEAK"
          }
        },
        {
          "zone_type": "ORDER_BLOCK",
          "price_min": 1.15692,
          "price_max": 1.156935,
          "timeframe": "1m",
          "origin_time": "1970-01-01T00:29:24.336540",
          "direction": "LONG",
          "role": "NEUTRAL",
          "strength": 3.0,
          "confidence": 0.5333333333333333,
          "components": [
            "orderblock",
            "leg_19_23"
          ],
          "zone_id": "ob_eurusd_1m_16_23",
          "entry_mode": "WICK_05",
          "quality": "WEAK",
          "reference_leg_id": "leg_19_23",
          "reference_event_id": null,
          "bias_at_creation": "LONG",
          "notes": "",
          "meta": {
            "body_pct": 0.3333333333333333,
            "wick_top_pct": 0.0,
            "wick_bottom_pct": 0.6666666666666666,
            "entry_mode": "WICK_05",
            "role": "NEUTRAL",
            "bias_at_creation": "LONG",
            "has_bos": false,
            "bar_count": 5,
            "amplitude": 0.00045999999999990493,
            "quality": "WEAK"
          }
        },
        {
          "zone_type": "ORDER_BLOCK",
          "price_min": 1.157245,
          "price_max": 1.15732,
          "timeframe": "1m",
          "origin_time": "1970-01-01T00:29:24.336960",
          "direction": "LONG",
          "role": "NEUTRAL",
          "strength": 3.0,
          "confidence": 0.6843749999998698,
          "components": [
            "orderblock",
            "leg_23_26"
          ],
          "zone_id": "ob_eurusd_1m_23_26",
          "entry_mode": "BODY_05",
          "quality": "WEAK",
          "reference_leg_id": "leg_23_26",
          "reference_event_id": null,
          "bias_at_creation": "LONG",
          "notes": "",
          "meta": {
            "body_pct": 0.9374999999994795,
            "wick_top_pct": 0.0,
            "wick_bottom_pct": 0.06250000000052042,
            "entry_mode": "BODY_05",
            "role": "NEUTRAL",
            "bias_at_creation": "LONG",
            "has_bos": false,
            "bar_count": 4,
            "amplitude": 0.00041499999999983217,
            "quality": "WEAK"
          }
        },
        {
          "zone_type": "ORDER_BLOCK",
          "price_min": 1.15691,
          "price_max": 1.15703,
          "timeframe": "1m",
          "origin_time": "1970-01-01T00:29:24.337140",
          "direction": "SHORT",
          "role": "NEUTRAL",
          "strength": 3.0,
          "confidence": 0.6807692307690993,
          "components": [
            "orderblock",
            "leg_26_28"
          ],
          "zone_id": "ob_eurusd_1m_26_28",
          "entry_mode": "BODY_05",
          "quality": "WEAK",
          "reference_leg_id": "leg_26_28",
          "reference_event_id": null,
          "bias_at_creation": "LONG",
          "notes": "",
          "meta": {
            "body_pct": 0.9230769230763975,
            "wick_top_pct": 0.03846153846180124,
            "wick_bottom_pct": 0.03846153846180124,
            "entry_mode": "BODY_05",
            "role": "NEUTRAL",
            "bias_at_creation": "LONG",
            "has_bos": false,
            "bar_count": 3,
            "amplitude": 0.0003449999999998177,
            "quality": "WEAK"
          }
        },
        {
          "zone_type": "ORDER_BLOCK",
          "price_min": 1.157005,
          "price_max": 1.15708,
          "timeframe": "1m",
          "origin_time": "1970-01-01T00:29:24.337080",
          "direction": "LONG",
          "role": "NEUTRAL",
          "strength": 1.7073170731696221,
          "confidence": 0.6375000000001387,
          "components": [
            "orderblock",
            "leg_28_30"
          ],
          "zone_id": "ob_eurusd_1m_25_30",
          "entry_mode": "BODY_05",
          "quality": "WEAK",
          "reference_leg_id": "leg_28_30",
          "reference_event_id": null,
          "bias_at_creation": "LONG",
          "notes": "",
          "meta": {
            "body_pct": 0.7500000000005551,
            "wick_top_pct": 0.049999999998112624,
            "wick_bottom_pct": 0.20000000000133228,
            "entry_mode": "BODY_05",
            "role": "NEUTRAL",
            "bias_at_creation": "LONG",
            "has_bos": false,
            "bar_count": 3,
            "amplitude": 0.0001749999999998142,
            "quality": "WEAK"
          }
        },
        {
          "zone_type": "ORDER_BLOCK",
          "price_min": 1.15709,
          "price_max": 1.1572149999999999,
          "timeframe": "1m",
          "origin_time": "1970-01-01T00:29:24.337380",
          "direction": "LONG",
          "role": "NEUTRAL",
          "strength": 3.0,
          "confidence": 0.6732142857144698,
          "components": [
            "orderblock",
            "leg_30_42"
          ],
          "zone_id": "ob_eurusd_1m_30_42",
          "entry_mode": "BODY_05",
          "quality": "WEAK",
          "reference_leg_id": "leg_30_42",
          "reference_event_id": null,
          "bias_at_creation": "LONG",
          "notes": "",
          "meta": {
            "body_pct": 0.8928571428578792,
            "wick_top_pct": 0.0,
            "wick_bottom_pct": 0.10714285714212077,
            "entry_mode": "BODY_05",
            "role": "NEUTRAL",
            "bias_at_creation": "LONG",
            "has_bos": false,
            "bar_count": 13,
            "amplitude": 0.00032999999999994145,
            "quality": "WEAK"
          }
        },
        {
          "zone_type": "ORDER_BLOCK",
          "price_min": 1.15748,
          "price_max": 1.1574900000000001,
          "timeframe": "1m",
          "origin_time": "1970-01-01T00:29:24.337980",
          "direction": "LONG",
          "role": "NEUTRAL",
          "strength": 3.0,
          "confidence": 0.6166666666691338,
          "components": [
            "orderblock",
            "leg_42_43"
          ],
          "zone_id": "ob_eurusd_1m_40_43",
          "entry_mode": "BODY_05",
          "quality": "WEAK",
          "reference_leg_id": "leg_42_43",
          "reference_event_id": null,
          "bias_at_creation": "LONG",
          "notes": "",
          "meta": {
            "body_pct": 0.6666666666765353,
            "wick_top_pct": 0.3333333333234647,
            "wick_bottom_pct": 0.0,
            "entry_mode": "BODY_05",
            "role": "NEUTRAL",
            "bias_at_creation": "LONG",
            "has_bos": false,
            "bar_count": 2,
            "amplitude": 0.00045000000000006146,
            "quality": "WEAK"
          }
        },
        {
          "zone_type": "ORDER_BLOCK",
          "price_min": 1.15784,
          "price_max": 1.157845,
          "timeframe": "1m",
          "origin_time": "1970-01-01T00:29:24.338160",
          "direction": "LONG",
          "role": "NEUTRAL",
          "strength": 3.0,
          "confidence": 0.47500000000011106,
          "components": [
            "orderblock",
            "leg_43_47"
          ],
          "zone_id": "ob_eurusd_1m_43_47",
          "entry_mode": "BODY_TOUCH",
          "quality": "WEAK",
          "reference_leg_id": "leg_43_47",
          "reference_event_id": null,
          "bias_at_creation": "LONG",
          "notes": "",
          "meta": {
            "body_pct": 0.1000000000004441,
            "wick_top_pct": 0.2000000000008882,
            "wick_bottom_pct": 0.6999999999986677,
            "entry_mode": "BODY_TOUCH",
            "role": "NEUTRAL",
            "bias_at_creation": "LONG",
            "has_bos": false,
            "bar_count": 5,
            "amplitude": 0.0003900000000001125,
            "quality": "WEAK"
          }
        },
        {
          "zone_type": "ORDER_BLOCK",
          "price_min": 1.1576,
          "price_max": 1.157655,
          "timeframe": "1m",
          "origin_time": "1970-01-01T00:29:24.338340",
          "direction": "LONG",
          "role": "NEUTRAL",
          "strength": 3.0,
          "confidence": 0.7,
          "components": [
            "orderblock",
            "leg_47_53"
          ],
          "zone_id": "ob_eurusd_1m_46_53",
          "entry_mode": "BODY_05",
          "quality": "WEAK",
          "reference_leg_id": "leg_47_53",
          "reference_event_id": null,
          "bias_at_creation": "LONG",
          "notes": "",
          "meta": {
            "body_pct": 1.0,
            "wick_top_pct": 0.0,
            "wick_bottom_pct": 0.0,
            "entry_mode": "BODY_05",
            "role": "NEUTRAL",
            "bias_at_creation": "LONG",
            "has_bos": false,
            "bar_count": 7,
            "amplitude": 0.0006749999999999812,
            "quality": "WEAK"
          }
        },
        {
          "zone_type": "ORDER_BLOCK",
          "price_min": 1.15813,
          "price_max": 1.15814,
          "timeframe": "1m",
          "origin_time": "1970-01-01T00:29:24.338760",
          "direction": "LONG",
          "role": "NEUTRAL",
          "strength": 3.0,
          "confidence": 0.6166666666654331,
          "components": [
            "orderblock",
            "leg_53_55"
          ],
          "zone_id": "ob_eurusd_1m_53_55",
          "entry_mode": "BODY_05",
          "quality": "WEAK",
          "reference_leg_id": "leg_53_55",
          "reference_event_id": null,
          "bias_at_creation": "LONG",
          "notes": "",
          "meta": {
            "body_pct": 0.6666666666617324,
            "wick_top_pct": 0.0,
            "wick_bottom_pct": 0.33333333333826765,
            "entry_mode": "BODY_05",
            "role": "NEUTRAL",
            "bias_at_creation": "LONG",
            "has_bos": false,
            "bar_count": 3,
            "amplitude": 0.0003349999999999742,
            "quality": "WEAK"
          }
        },
        {
          "zone_type": "ORDER_BLOCK",
          "price_min": 1.15788,
          "price_max": 1.157915,
          "timeframe": "1m",
          "origin_time": "1970-01-01T00:29:24.339180",
          "direction": "SHORT",
          "role": "NEUTRAL",
          "strength": 1.8048780487800575,
          "confidence": 0.5571428571435368,
          "components": [
            "orderblock",
            "leg_60_62"
          ],
          "zone_id": "ob_eurusd_1m_60_62",
          "entry_mode": "WICK_TOUCH",
          "quality": "WEAK",
          "reference_leg_id": "leg_60_62",
          "reference_event_id": null,
          "bias_at_creation": "LONG",
          "notes": "",
          "meta": {
            "body_pct": 0.4285714285741475,
            "wick_top_pct": 0.14285714285804915,
            "wick_bottom_pct": 0.42857142856780334,
            "entry_mode": "WICK_TOUCH",
            "role": "NEUTRAL",
            "bias_at_creation": "LONG",
            "has_bos": false,
            "bar_count": 3,
            "amplitude": 0.0001849999999998797,
            "quality": "WEAK"
          }
        },
        {
          "zone_type": "ORDER_BLOCK",
          "price_min": 1.15799,
          "price_max": 1.158055,
          "timeframe": "1m",
          "origin_time": "1970-01-01T00:29:24.339300",
          "direction": "SHORT",
          "role": "NEUTRAL",
          "strength": 3.0,
          "confidence": 0.6411764705884274,
          "components": [
            "orderblock",
            "leg_62_77"
          ],
          "zone_id": "ob_eurusd_1m_62_77",
          "entry_mode": "BODY_05",
          "quality": "WEAK",
          "reference_leg_id": "leg_62_77",
          "reference_event_id": null,
          "bias_at_creation": "LONG",
          "notes": "",
          "meta": {
            "body_pct": 0.7647058823537095,
            "wick_top_pct": 0.11764705882183911,
            "wick_bottom_pct": 0.1176470588244514,
            "entry_mode": "BODY_05",
            "role": "NEUTRAL",
            "bias_at_creation": "LONG",
            "has_bos": false,
            "bar_count": 16,
            "amplitude": 0.0009249999999998426,
            "quality": "WEAK"
          }
        },
        {
          "zone_type": "ORDER_BLOCK",
          "price_min": 1.157195,
          "price_max": 1.1572,
          "timeframe": "1m",
          "origin_time": "1970-01-01T00:29:24.340200",
          "direction": "SHORT",
          "role": "NEUTRAL",
          "strength": 3.0,
          "confidence": 0.4692307692309006,
          "components": [
            "orderblock",
            "leg_77_86"
          ],
          "zone_id": "ob_eurusd_1m_77_86",
          "entry_mode": "BODY_TOUCH",
          "quality": "WEAK",
          "reference_leg_id": "leg_77_86",
          "reference_event_id": null,
          "bias_at_creation": "LONG",
          "notes": "",
          "meta": {
            "body_pct": 0.07692307692360248,
            "wick_top_pct": 0.07692307692360248,
            "wick_bottom_pct": 0.8461538461527951,
            "entry_mode": "BODY_TOUCH",
            "role": "NEUTRAL",
            "bias_at_creation": "LONG",
            "has_bos": false,
            "bar_count": 10,
            "amplitude": 0.0006299999999999084,
            "quality": "WEAK"
          }
        },
        {
          "zone_type": "ORDER_BLOCK",
          "price_min": 1.15774,
          "price_max": 1.157765,
          "timeframe": "1m",
          "origin_time": "1970-01-01T00:29:24.340740",
          "direction": "LONG",
          "role": "NEUTRAL",
          "strength": 2.926829268293566,
          "confidence": 0.658333333333025,
          "components": [
            "orderblock",
            "leg_86_87"
          ],
          "zone_id": "ob_eurusd_1m_86_87",
          "entry_mode": "BODY_05",
          "quality": "WEAK",
          "reference_leg_id": "leg_86_87",
          "reference_event_id": null,
          "bias_at_creation": "LONG",
          "notes": "",
          "meta": {
            "body_pct": 0.8333333333320998,
            "wick_top_pct": 0.16666666666790025,
            "wick_bottom_pct": 0.0,
            "entry_mode": "BODY_05",
            "role": "NEUTRAL",
            "bias_at_creation": "LONG",
            "has_bos": false,
            "bar_count": 2,
            "amplitude": 0.00029999999999996696,
            "quality": "WEAK"
          }
        },
        {
          "zone_type": "ORDER_BLOCK",
          "price_min": 1.15761,
          "price_max": 1.15762,
          "timeframe": "1m",
          "origin_time": "1970-01-01T00:29:24.340680",
          "direction": "SHORT",
          "role": "NEUTRAL",
          "strength": 0.87804878048742,
          "confidence": 0.575,
          "components": [
            "orderblock",
            "leg_87_93"
          ],
          "zone_id": "ob_eurusd_1m_85_93",
          "entry_mode": "WICK_TOUCH",
          "quality": "WEAK",
          "reference_leg_id": "leg_87_93",
          "reference_event_id": null,
          "bias_at_creation": "LONG",
          "notes": "",
          "meta": {
            "body_pct": 0.5,
            "wick_top_pct": 0.0,
            "wick_bottom_pct": 0.5,
            "entry_mode": "WICK_TOUCH",
            "role": "NEUTRAL",
            "bias_at_creation": "LONG",
            "has_bos": false,
            "bar_count": 7,
            "amplitude": 8.999999999992347e-05,
            "quality": "WEAK"
          }
        },
        {
          "zone_type": "ORDER_BLOCK",
          "price_min": 1.157365,
          "price_max": 1.157555,
          "timeframe": "1m",
          "origin_time": "1970-01-01T00:29:24.341160",
          "direction": "LONG",
          "role": "NEUTRAL",
          "strength": 3.0,
          "confidence": 0.6935897435896998,
          "components": [
            "orderblock",
            "leg_93_105"
          ],
          "zone_id": "ob_eurusd_1m_93_105",
          "entry_mode": "BODY_05",
          "quality": "WEAK",
          "reference_leg_id": "leg_93_105",
          "reference_event_id": null,
          "bias_at_creation": "LONG",
          "notes": "",
          "meta": {
            "body_pct": 0.9743589743587991,
            "wick_top_pct": 0.025641025641200823,
            "wick_bottom_pct": 0.0,
            "entry_mode": "BODY_05",
            "role": "NEUTRAL",
            "bias_at_creation": "LONG",
            "has_bos": false,
            "bar_count": 13,
            "amplitude": 0.0011350000000001081,
            "quality": "WEAK"
          }
        },
        {
          "zone_type": "ORDER_BLOCK",
          "price_min": 1.158405,
          "price_max": 1.158455,
          "timeframe": "1m",
          "origin_time": "1970-01-01T00:29:24.342000",
          "direction": "LONG",
          "role": "NEUTRAL",
          "strength": 2.975609756098784,
          "confidence": 0.6583333333339502,
          "components": [
            "orderblock",
            "leg_109_113"
          ],
          "zone_id": "ob_eurusd_1m_107_113",
          "entry_mode": "BODY_05",
          "quality": "WEAK",
          "reference_leg_id": "leg_109_113",
          "reference_event_id": null,
          "bias_at_creation": "LONG",
          "notes": "",
          "meta": {
            "body_pct": 0.8333333333358005,
            "wick_top_pct": 0.0,
            "wick_bottom_pct": 0.1666666666641995,
            "entry_mode": "BODY_05",
            "role": "NEUTRAL",
            "bias_at_creation": "LONG",
            "has_bos": false,
            "bar_count": 5,
            "amplitude": 0.0003049999999999997,
            "quality": "WEAK"
          }
        },
        {
          "zone_type": "ORDER_BLOCK",
          "price_min": 1.158755,
          "price_max": 1.158815,
          "timeframe": "1m",
          "origin_time": "1970-01-01T00:29:24.342360",
          "direction": "LONG",
          "role": "NEUTRAL",
          "strength": 3.0,
          "confidence": 0.5333333333330249,
          "components": [
            "orderblock",
            "leg_113_117"
          ],
          "zone_id": "ob_eurusd_1m_113_117",
          "entry_mode": "WICK_05",
          "quality": "WEAK",
          "reference_leg_id": "leg_113_117",
          "reference_event_id": null,
          "bias_at_creation": "LONG",
          "notes": "",
          "meta": {
            "body_pct": 0.33333333333209975,
            "wick_top_pct": 0.5,
            "wick_bottom_pct": 0.16666666666790025,
            "entry_mode": "WICK_05",
            "role": "NEUTRAL",
            "bias_at_creation": "LONG",
            "has_bos": false,
            "bar_count": 5,
            "amplitude": 0.0008049999999999446,
            "quality": "WEAK"
          }
        },
        {
          "zone_type": "ORDER_BLOCK",
          "price_min": 1.15802,
          "price_max": 1.158205,
          "timeframe": "1m",
          "origin_time": "1970-01-01T00:29:24.342600",
          "direction": "SHORT",
          "role": "NEUTRAL",
          "strength": 3.0,
          "confidence": 0.6871794871793996,
          "components": [
            "orderblock",
            "leg_117_121"
          ],
          "zone_id": "ob_eurusd_1m_117_121",
          "entry_mode": "BODY_05",
          "quality": "WEAK",
          "reference_leg_id": "leg_117_121",
          "reference_event_id": null,
          "bias_at_creation": "LONG",
          "notes": "",
          "meta": {
            "body_pct": 0.9487179487175984,
            "wick_top_pct": 0.0,
            "wick_bottom_pct": 0.051282051282401646,
            "entry_mode": "BODY_05",
            "role": "NEUTRAL",
            "bias_at_creation": "LONG",
            "has_bos": false,
            "bar_count": 5,
            "amplitude": 0.00036999999999998145,
            "quality": "WEAK"
          }
        },
        {
          "zone_type": "ORDER_BLOCK",
          "price_min": 1.15829,
          "price_max": 1.158305,
          "timeframe": "1m",
          "origin_time": "1970-01-01T00:29:24.343080",
          "direction": "LONG",
          "role": "NEUTRAL",
          "strength": 2.341463414635286,
          "confidence": 0.6374999999993061,
          "components": [
            "orderblock",
            "leg_125_127"
          ],
          "zone_id": "ob_eurusd_1m_125_127",
          "entry_mode": "BODY_05",
          "quality": "WEAK",
          "reference_leg_id": "leg_125_127",
          "reference_event_id": null,
          "bias_at_creation": "LONG",
          "notes": "",
          "meta": {
            "body_pct": 0.7499999999972244,
            "wick_top_pct": 0.25000000000277556,
            "wick_bottom_pct": 0.0,
            "entry_mode": "BODY_05",
            "role": "NEUTRAL",
            "bias_at_creation": "LONG",
            "has_bos": false,
            "bar_count": 3,
            "amplitude": 0.00024000000000001798,
            "quality": "WEAK"
          }
        },
        {
          "zone_type": "ORDER_BLOCK",
          "price_min": 1.15809,
          "price_max": 1.15821,
          "timeframe": "1m",
          "origin_time": "1970-01-01T00:29:24.343200",
          "direction": "SHORT",
          "role": "NEUTRAL",
          "strength": 2.2926829268300684,
          "confidence": 0.656896551723874,
          "components": [
            "orderblock",
            "leg_127_129"
          ],
          "zone_id": "ob_eurusd_1m_127_129",
          "entry_mode": "BODY_05",
          "quality": "WEAK",
          "reference_leg_id": "leg_127_129",
          "reference_event_id": null,
          "bias_at_creation": "LONG",
          "notes": "",
          "meta": {
            "body_pct": 0.8275862068954957,
            "wick_top_pct": 0.034482758620900875,
            "wick_bottom_pct": 0.1379310344836035,
            "entry_mode": "BODY_05",
            "role": "NEUTRAL",
            "bias_at_creation": "LONG",
            "has_bos": false,
            "bar_count": 3,
            "amplitude": 0.00023499999999998522,
            "quality": "WEAK"
          }
        },
        {
          "zone_type": "ORDER_BLOCK",
          "price_min": 1.158265,
          "price_max": 1.158305,
          "timeframe": "1m",
          "origin_time": "1970-01-01T00:29:24.343320",
          "direction": "SHORT",
          "role": "NEUTRAL",
          "strength": 2.3902439024383377,
          "confidence": 0.6062500000017348,
          "components": [
            "orderblock",
            "leg_129_131"
          ],
          "zone_id": "ob_eurusd_1m_129_131",
          "entry_mode": "WICK_TOUCH",
          "quality": "WEAK",
          "reference_leg_id": "leg_129_131",
          "reference_event_id": null,
          "bias_at_creation": "LONG",
          "notes": "",
          "meta": {
            "body_pct": 0.6250000000069389,
            "wick_top_pct": 0.24999999999722444,
            "wick_bottom_pct": 0.12499999999583666,
            "entry_mode": "WICK_TOUCH",
            "role": "NEUTRAL",
            "bias_at_creation": "LONG",
            "has_bos": false,
            "bar_count": 3,
            "amplitude": 0.0002449999999998287,
            "quality": "WEAK"
          }
        },
        {
          "zone_type": "ORDER_BLOCK",
          "price_min": 1.158065,
          "price_max": 1.158145,
          "timeframe": "1m",
          "origin_time": "1970-01-01T00:29:24.343440",
          "direction": "LONG",
          "role": "NEUTRAL",
          "strength": 3.0,
          "confidence": 0.6722222222226334,
          "components": [
            "orderblock",
            "leg_131_139"
          ],
          "zone_id": "ob_eurusd_1m_131_139",
          "entry_mode": "BODY_05",
          "quality": "WEAK",
          "reference_leg_id": "leg_131_139",
          "reference_event_id": null,
          "bias_at_creation": "LONG",
          "notes": "",
          "meta": {
            "body_pct": 0.8888888888905336,
            "wick_top_pct": 0.05555555555596675,
            "wick_bottom_pct": 0.055555555553499586,
            "entry_mode": "BODY_05",
            "role": "NEUTRAL",
            "bias_at_creation": "LONG",
            "has_bos": false,
            "bar_count": 9,
            "amplitude": 0.0007599999999998719,
            "quality": "WEAK"
          }
        },
        {
          "zone_type": "ORDER_BLOCK",
          "price_min": 1.15845,
          "price_max": 1.1584699999999999,
          "timeframe": "1m",
          "origin_time": "1970-01-01T00:29:24.343740",
          "direction": "LONG",
          "role": "NEUTRAL",
          "strength": 3.0,
          "confidence": 0.6499999999995559,
          "components": [
            "orderblock",
            "leg_139_141"
          ],
          "zone_id": "ob_eurusd_1m_136_141",
          "entry_mode": "BODY_05",
          "quality": "WEAK",
          "reference_leg_id": "leg_139_141",
          "reference_event_id": null,
          "bias_at_creation": "LONG",
          "notes": "",
          "meta": {
            "body_pct": 0.7999999999982237,
            "wick_top_pct": 0.0,
            "wick_bottom_pct": 0.20000000000177637,
            "entry_mode": "BODY_05",
            "role": "NEUTRAL",
            "bias_at_creation": "LONG",
            "has_bos": false,
            "bar_count": 3,
            "amplitude": 0.0006450000000000067,
            "quality": "WEAK"
          }
        },
        {
          "zone_type": "ORDER_BLOCK",
          "price_min": 1.15845,
          "price_max": 1.1584699999999999,
          "timeframe": "1m",
          "origin_time": "1970-01-01T00:29:24.343740",
          "direction": "LONG",
          "role": "NEUTRAL",
          "strength": 3.0,
          "confidence": 0.6499999999995559,
          "components": [
            "orderblock",
            "leg_141_148"
          ],
          "zone_id": "ob_eurusd_1m_136_148",
          "entry_mode": "BODY_05",
          "quality": "WEAK",
          "reference_leg_id": "leg_141_148",
          "reference_event_id": null,
          "bias_at_creation": "LONG",
          "notes": "",
          "meta": {
            "body_pct": 0.7999999999982237,
            "wick_top_pct": 0.0,
            "wick_bottom_pct": 0.20000000000177637,
            "entry_mode": "BODY_05",
            "role": "NEUTRAL",
            "bias_at_creation": "LONG",
            "has_bos": false,
            "bar_count": 8,
            "amplitude": 0.0008099999999999774,
            "quality": "WEAK"
          }
        },
        {
          "zone_type": "ORDER_BLOCK",
          "price_min": 1.1584349999999999,
          "price_max": 1.15845,
          "timeframe": "1m",
          "origin_time": "1970-01-01T00:29:24.344100",
          "direction": "LONG",
          "role": "NEUTRAL",
          "strength": 3.0,
          "confidence": 0.6375,
          "components": [
            "orderblock",
            "leg_148_150"
          ],
          "zone_id": "ob_eurusd_1m_142_150",
          "entry_mode": "BODY_05",
          "quality": "WEAK",
          "reference_leg_id": "leg_148_150",
          "reference_event_id": null,
          "bias_at_creation": "LONG",
          "notes": "",
          "meta": {
            "body_pct": 0.75,
            "wick_top_pct": 0.25,
            "wick_bottom_pct": 0.0,
            "entry_mode": "BODY_05",
            "role": "NEUTRAL",
            "bias_at_creation": "LONG",
            "has_bos": false,
            "bar_count": 3,
            "amplitude": 0.0003549999999998832,
            "quality": "WEAK"
          }
        },
        {
          "zone_type": "ORDER_BLOCK",
          "price_min": 1.15863,
          "price_max": 1.158645,
          "timeframe": "1m",
          "origin_time": "1970-01-01T00:29:24.344580",
          "direction": "LONG",
          "role": "NEUTRAL",
          "strength": 3.0,
          "confidence": 0.7,
          "components": [
            "orderblock",
            "leg_150_167"
          ],
          "zone_id": "ob_eurusd_1m_150_167",
          "entry_mode": "BODY_05",
          "quality": "WEAK",
          "reference_leg_id": "leg_150_167",
          "reference_event_id": null,
          "bias_at_creation": "LONG",
          "notes": "",
          "meta": {
            "body_pct": 1.0,
            "wick_top_pct": 0.0,
            "wick_bottom_pct": 0.0,
            "entry_mode": "BODY_05",
            "role": "NEUTRAL",
            "bias_at_creation": "LONG",
            "has_bos": false,
            "bar_count": 18,
            "amplitude": 0.0021199999999998997,
            "quality": "WEAK"
          }
        },
        {
          "zone_type": "ORDER_BLOCK",
          "price_min": 1.160725,
          "price_max": 1.16075,
          "timeframe": "1m",
          "origin_time": "1970-01-01T00:29:24.345600",
          "direction": "LONG",
          "role": "NEUTRAL",
          "strength": 3.0,
          "confidence": 0.5999999999991118,
          "components": [
            "orderblock",
            "leg_167_170"
          ],
          "zone_id": "ob_eurusd_1m_167_170",
          "entry_mode": "WICK_05",
          "quality": "WEAK",
          "reference_leg_id": "leg_167_170",
          "reference_event_id": null,
          "bias_at_creation": "LONG",
          "notes": "",
          "meta": {
            "body_pct": 0.5999999999964473,
            "wick_top_pct": 0.20000000000177637,
            "wick_bottom_pct": 0.20000000000177637,
            "entry_mode": "WICK_05",
            "role": "NEUTRAL",
            "bias_at_creation": "LONG",
            "has_bos": false,
            "bar_count": 4,
            "amplitude": 0.0007699999999999374,
            "quality": "WEAK"
          }
        },
        {
          "zone_type": "ORDER_BLOCK",
          "price_min": 1.160435,
          "price_max": 1.16045,
          "timeframe": "1m",
          "origin_time": "1970-01-01T00:29:24.345720",
          "direction": "SHORT",
          "role": "NEUTRAL",
          "strength": 2.097560975611364,
          "confidence": 0.6374999999993061,
          "components": [
            "orderblock",
            "leg_170_173"
          ],
          "zone_id": "ob_eurusd_1m_169_173",
          "entry_mode": "BODY_05",
          "quality": "WEAK",
          "reference_leg_id": "leg_170_173",
          "reference_event_id": null,
          "bias_at_creation": "LONG",
          "notes": "",
          "meta": {
            "body_pct": 0.7499999999972244,
            "wick_top_pct": 0.0,
            "wick_bottom_pct": 0.25000000000277556,
            "entry_mode": "BODY_05",
            "role": "NEUTRAL",
            "bias_at_creation": "LONG",
            "has_bos": false,
            "bar_count": 4,
            "amplitude": 0.00021500000000007624,
            "quality": "WEAK"
          }
        },
        {
          "zone_type": "ORDER_BLOCK",
          "price_min": 1.16018,
          "price_max": 1.160195,
          "timeframe": "1m",
          "origin_time": "1970-01-01T00:29:24.345960",
          "direction": "SHORT",
          "role": "NEUTRAL",
          "strength": 3.0,
          "confidence": 0.5333333333333333,
          "components": [
            "orderblock",
            "leg_173_176"
          ],
          "zone_id": "ob_eurusd_1m_173_176",
          "entry_mode": "WICK_TOUCH",
          "quality": "WEAK",
          "reference_leg_id": "leg_173_176",
          "reference_event_id": null,
          "bias_at_creation": "LONG",
          "notes": "",
          "meta": {
            "body_pct": 0.3333333333333333,
            "wick_top_pct": 0.0,
            "wick_bottom_pct": 0.6666666666666666,
            "entry_mode": "WICK_TOUCH",
            "role": "NEUTRAL",
            "bias_at_creation": "LONG",
            "has_bos": false,
            "bar_count": 4,
            "amplitude": 0.00031500000000006523,
            "quality": "WEAK"
          }
        },
        {
          "zone_type": "ORDER_BLOCK",
          "price_min": 1.15988,
          "price_max": 1.1599,
          "timeframe": "1m",
          "origin_time": "1970-01-01T00:29:24.346140",
          "direction": "LONG",
          "role": "NEUTRAL",
          "strength": 3.0,
          "confidence": 0.5125000000006938,
          "components": [
            "orderblock",
            "leg_176_179"
          ],
          "zone_id": "ob_eurusd_1m_176_179",
          "entry_mode": "WICK_05",
          "quality": "WEAK",
          "reference_leg_id": "leg_176_179",
          "reference_event_id": null,
          "bias_at_creation": "LONG",
          "notes": "",
          "meta": {
            "body_pct": 0.25000000000277556,
            "wick_top_pct": 0.4999999999944489,
            "wick_bottom_pct": 0.25000000000277556,
            "entry_mode": "WICK_05",
            "role": "NEUTRAL",
            "bias_at_creation": "LONG",
            "has_bos": false,
            "bar_count": 4,
            "amplitude": 0.0005599999999998939,
            "quality": "WEAK"
          }
        },
        {
          "zone_type": "ORDER_BLOCK",
          "price_min": 1.16036,
          "price_max": 1.16044,
          "timeframe": "1m",
          "origin_time": "1970-01-01T00:29:24.346320",
          "direction": "SHORT",
          "role": "NEUTRAL",
          "strength": 3.0,
          "confidence": 0.6852941176469436,
          "components": [
            "orderblock",
            "leg_179_186"
          ],
          "zone_id": "ob_eurusd_1m_179_186",
          "entry_mode": "BODY_05",
          "quality": "WEAK",
          "reference_leg_id": "leg_179_186",
          "reference_event_id": null,
          "bias_at_creation": "LONG",
          "notes": "",
          "meta": {
            "body_pct": 0.9411764705877743,
            "wick_top_pct": 0.0,
            "wick_bottom_pct": 0.0588235294122257,
            "entry_mode": "BODY_05",
            "role": "NEUTRAL",
            "bias_at_creation": "LONG",
            "has_bos": false,
            "bar_count": 8,
            "amplitude": 0.0008849999999998026,
            "quality": "WEAK"
          }
        },
        {
          "zone_type": "ORDER_BLOCK",
          "price_min": 1.1595550000000001,
          "price_max": 1.15958,
          "timeframe": "1m",
          "origin_time": "1970-01-01T00:29:24.346740",
          "direction": "SHORT",
          "role": "NEUTRAL",
          "strength": 3.0,
          "confidence": 0.658333333333025,
          "components": [
            "orderblock",
            "leg_186_189"
          ],
          "zone_id": "ob_eurusd_1m_186_189",
          "entry_mode": "BODY_05",
          "quality": "WEAK",
          "reference_leg_id": "leg_186_189",
          "reference_event_id": null,
          "bias_at_creation": "LONG",
          "notes": "",
          "meta": {
            "body_pct": 0.8333333333320998,
            "wick_top_pct": 0.16666666666790025,
            "wick_bottom_pct": 0.0,
            "entry_mode": "BODY_05",
            "role": "NEUTRAL",
            "bias_at_creation": "LONG",
            "has_bos": false,
            "bar_count": 4,
            "amplitude": 0.00030999999999981043,
            "quality": "WEAK"
          }
        },
        {
          "zone_type": "ORDER_BLOCK",
          "price_min": 1.159815,
          "price_max": 1.15982,
          "timeframe": "1m",
          "origin_time": "1970-01-01T00:29:24.346920",
          "direction": "SHORT",
          "role": "NEUTRAL",
          "strength": 3.0,
          "confidence": 0.47272727272745624,
          "components": [
            "orderblock",
            "leg_189_191"
          ],
          "zone_id": "ob_eurusd_1m_189_191",
          "entry_mode": "BODY_TOUCH",
          "quality": "WEAK",
          "reference_leg_id": "leg_189_191",
          "reference_event_id": null,
          "bias_at_creation": "LONG",
          "notes": "",
          "meta": {
            "body_pct": 0.09090909090982494,
            "wick_top_pct": 0.8181818181803501,
            "wick_bottom_pct": 0.09090909090982494,
            "entry_mode": "BODY_TOUCH",
            "role": "NEUTRAL",
            "bias_at_creation": "LONG",
            "has_bos": false,
            "bar_count": 3,
            "amplitude": 0.00032999999999994145,
            "quality": "WEAK"
          }
        },
        {
          "zone_type": "ORDER_BLOCK",
          "price_min": 1.15954,
          "price_max": 1.15955,
          "timeframe": "1m",
          "origin_time": "1970-01-01T00:29:24.347040",
          "direction": "LONG",
          "role": "NEUTRAL",
          "strength": 3.0,
          "confidence": 0.6166666666666667,
          "components": [
            "orderblock",
            "leg_192_196"
          ],
          "zone_id": "ob_eurusd_1m_191_196",
          "entry_mode": "BODY_05",
          "quality": "WEAK",
          "reference_leg_id": "leg_192_196",
          "reference_event_id": null,
          "bias_at_creation": "LONG",
          "notes": "",
          "meta": {
            "body_pct": 0.6666666666666666,
            "wick_top_pct": 0.0,
            "wick_bottom_pct": 0.3333333333333333,
            "entry_mode": "BODY_05",
            "role": "NEUTRAL",
            "bias_at_creation": "LONG",
            "has_bos": false,
            "bar_count": 5,
            "amplitude": 0.00041000000000002146,
            "quality": "WEAK"
          }
        },
        {
          "zone_type": "ORDER_BLOCK",
          "price_min": 1.15988,
          "price_max": 1.1599300000000001,
          "timeframe": "1m",
          "origin_time": "1970-01-01T00:29:24.347340",
          "direction": "SHORT",
          "role": "NEUTRAL",
          "strength": 3.0,
          "confidence": 0.6423076923081522,
          "components": [
            "orderblock",
            "leg_196_198"
          ],
          "zone_id": "ob_eurusd_1m_196_198",
          "entry_mode": "BODY_05",
          "quality": "WEAK",
          "reference_leg_id": "leg_196_198",
          "reference_event_id": null,
          "bias_at_creation": "LONG",
          "notes": "",
          "meta": {
            "body_pct": 0.7692307692326087,
            "wick_top_pct": 0.23076923076739134,
            "wick_bottom_pct": 0.0,
            "entry_mode": "BODY_05",
            "role": "NEUTRAL",
            "bias_at_creation": "LONG",
            "has_bos": false,
            "bar_count": 3,
            "amplitude": 0.0005649999999999267,
            "quality": "WEAK"
          }
        },
        {
          "zone_type": "ORDER_BLOCK",
          "price_min": 1.15975,
          "price_max": 1.159765,
          "timeframe": "1m",
          "origin_time": "1970-01-01T00:29:24.347220",
          "direction": "LONG",
          "role": "NEUTRAL",
          "strength": 3.0,
          "confidence": 0.7,
          "components": [
            "orderblock",
            "leg_198_209"
          ],
          "zone_id": "ob_eurusd_1m_194_209",
          "entry_mode": "BODY_05",
          "quality": "WEAK",
          "reference_leg_id": "leg_198_209",
          "reference_event_id": null,
          "bias_at_creation": "LONG",
          "notes": "",
          "meta": {
            "body_pct": 1.0,
            "wick_top_pct": 0.0,
            "wick_bottom_pct": 0.0,
            "entry_mode": "BODY_05",
            "role": "NEUTRAL",
            "bias_at_creation": "LONG",
            "has_bos": false,
            "bar_count": 12,
            "amplitude": 0.0009399999999999409,
            "quality": "WEAK"
          }
        },
        {
          "zone_type": "ORDER_BLOCK",
          "price_min": 1.160205,
          "price_max": 1.16024,
          "timeframe": "1m",
          "origin_time": "1970-01-01T00:29:24.348060",
          "direction": "LONG",
          "role": "NEUTRAL",
          "strength": 2.5365853658539907,
          "confidence": 0.7,
          "components": [
            "orderblock",
            "leg_209_211"
          ],
          "zone_id": "ob_eurusd_1m_208_211",
          "entry_mode": "BODY_05",
          "quality": "WEAK",
          "reference_leg_id": "leg_209_211",
          "reference_event_id": null,
          "bias_at_creation": "LONG",
          "notes": "",
          "meta": {
            "body_pct": 1.0,
            "wick_top_pct": 0.0,
            "wick_bottom_pct": 0.0,
            "entry_mode": "BODY_05",
            "role": "NEUTRAL",
            "bias_at_creation": "LONG",
            "has_bos": false,
            "bar_count": 3,
            "amplitude": 0.00025999999999992696,
            "quality": "WEAK"
          }
        },
        {
          "zone_type": "ORDER_BLOCK",
          "price_min": 1.16006,
          "price_max": 1.16009,
          "timeframe": "1m",
          "origin_time": "1970-01-01T00:29:24.348240",
          "direction": "SHORT",
          "role": "NEUTRAL",
          "strength": 2.34146341463312,
          "confidence": 0.6375000000006938,
          "components": [
            "orderblock",
            "leg_211_213"
          ],
          "zone_id": "ob_eurusd_1m_211_213",
          "entry_mode": "BODY_05",
          "quality": "WEAK",
          "reference_leg_id": "leg_211_213",
          "reference_event_id": null,
          "bias_at_creation": "LONG",
          "notes": "",
          "meta": {
            "body_pct": 0.7500000000027756,
            "wick_top_pct": 0.24999999999722444,
            "wick_bottom_pct": 0.0,
            "entry_mode": "BODY_05",
            "role": "NEUTRAL",
            "bias_at_creation": "LONG",
            "has_bos": false,
            "bar_count": 3,
            "amplitude": 0.00023999999999979593,
            "quality": "WEAK"
          }
        },
        {
          "zone_type": "ORDER_BLOCK",
          "price_min": 1.16024,
          "price_max": 1.160295,
          "timeframe": "1m",
          "origin_time": "1970-01-01T00:29:24.348540",
          "direction": "LONG",
          "role": "NEUTRAL",
          "strength": 1.0731707317061245,
          "confidence": 0.6615384615390528,
          "components": [
            "orderblock",
            "leg_216_218"
          ],
          "zone_id": "ob_eurusd_1m_216_218",
          "entry_mode": "BODY_05",
          "quality": "WEAK",
          "reference_leg_id": "leg_216_218",
          "reference_event_id": null,
          "bias_at_creation": "LONG",
          "notes": "",
          "meta": {
            "body_pct": 0.8461538461562111,
            "wick_top_pct": 0.0769230769201864,
            "wick_bottom_pct": 0.07692307692360248,
            "entry_mode": "BODY_05",
            "role": "NEUTRAL",
            "bias_at_creation": "LONG",
            "has_bos": false,
            "bar_count": 3,
            "amplitude": 0.00010999999999983245,
            "quality": "WEAK"
          }
        },
        {
          "zone_type": "ORDER_BLOCK",
          "price_min": 1.16019,
          "price_max": 1.16021,
          "timeframe": "1m",
          "origin_time": "1970-01-01T00:29:24.348660",
          "direction": "LONG",
          "role": "NEUTRAL",
          "strength": 1.5609756097561354,
          "confidence": 0.7,
          "components": [
            "orderblock",
            "leg_218_220"
          ],
          "zone_id": "ob_eurusd_1m_218_220",
          "entry_mode": "BODY_05",
          "quality": "WEAK",
          "reference_leg_id": "leg_218_220",
          "reference_event_id": null,
          "bias_at_creation": "LONG",
          "notes": "",
          "meta": {
            "body_pct": 1.0,
            "wick_top_pct": 0.0,
            "wick_bottom_pct": 0.0,
            "entry_mode": "BODY_05",
            "role": "NEUTRAL",
            "bias_at_creation": "LONG",
            "has_bos": false,
            "bar_count": 3,
            "amplitude": 0.00015999999999993797,
            "quality": "WEAK"
          }
        },
        {
          "zone_type": "ORDER_BLOCK",
          "price_min": 1.160195,
          "price_max": 1.1602649999999999,
          "timeframe": "1m",
          "origin_time": "1970-01-01T00:29:24.348720",
          "direction": "SHORT",
          "role": "NEUTRAL",
          "strength": 3.0,
          "confidence": 0.6687499999997398,
          "components": [
            "orderblock",
            "leg_220_224"
          ],
          "zone_id": "ob_eurusd_1m_219_224",
          "entry_mode": "BODY_05",
          "quality": "WEAK",
          "reference_leg_id": "leg_220_224",
          "reference_event_id": null,
          "bias_at_creation": "LONG",
          "notes": "",
          "meta": {
            "body_pct": 0.8749999999989592,
            "wick_top_pct": 0.12500000000104083,
            "wick_bottom_pct": 0.0,
            "entry_mode": "BODY_05",
            "role": "NEUTRAL",
            "bias_at_creation": "LONG",
            "has_bos": false,
            "bar_count": 5,
            "amplitude": 0.0006099999999999994,
            "quality": "WEAK"
          }
        },
        {
          "zone_type": "ORDER_BLOCK",
          "price_min": 1.159885,
          "price_max": 1.15989,
          "timeframe": "1m",
          "origin_time": "1970-01-01T00:29:24.348960",
          "direction": "SHORT",
          "role": "NEUTRAL",
          "strength": 2.5853658536592086,
          "confidence": 0.7,
          "components": [
            "orderblock",
            "leg_224_229"
          ],
          "zone_id": "ob_eurusd_1m_223_229",
          "entry_mode": "BODY_05",
          "quality": "WEAK",
          "reference_leg_id": "leg_224_229",
          "reference_event_id": null,
          "bias_at_creation": "LONG",
          "notes": "",
          "meta": {
            "body_pct": 1.0,
            "wick_top_pct": 0.0,
            "wick_bottom_pct": 0.0,
            "entry_mode": "BODY_05",
            "role": "NEUTRAL",
            "bias_at_creation": "LONG",
            "has_bos": false,
            "bar_count": 6,
            "amplitude": 0.0002649999999999597,
            "quality": "WEAK"
          }
        },
        {
          "zone_type": "ORDER_BLOCK",
          "price_min": 1.15987,
          "price_max": 1.159915,
          "timeframe": "1m",
          "origin_time": "1970-01-01T00:29:24.349260",
          "direction": "SHORT",
          "role": "NEUTRAL",
          "strength": 3.0,
          "confidence": 0.6374999999997687,
          "components": [
            "orderblock",
            "leg_229_234"
          ],
          "zone_id": "ob_eurusd_1m_228_234",
          "entry_mode": "BODY_05",
          "quality": "WEAK",
          "reference_leg_id": "leg_229_234",
          "reference_event_id": null,
          "bias_at_creation": "LONG",
          "notes": "",
          "meta": {
            "body_pct": 0.7499999999990749,
            "wick_top_pct": 0.2500000000009252,
            "wick_bottom_pct": 0.0,
            "entry_mode": "BODY_05",
            "role": "NEUTRAL",
            "bias_at_creation": "LONG",
            "has_bos": false,
            "bar_count": 6,
            "amplitude": 0.00048499999999984666,
            "quality": "WEAK"
          }
        },
        {
          "zone_type": "ORDER_BLOCK",
          "price_min": 1.15952,
          "price_max": 1.159525,
          "timeframe": "1m",
          "origin_time": "1970-01-01T00:29:24.349620",
          "direction": "SHORT",
          "role": "NEUTRAL",
          "strength": 3.0,
          "confidence": 0.7,
          "components": [
            "orderblock",
            "leg_234_238"
          ],
          "zone_id": "ob_eurusd_1m_234_238",
          "entry_mode": "BODY_05",
          "quality": "WEAK",
          "reference_leg_id": "leg_234_238",
          "reference_event_id": null,
          "bias_at_creation": "LONG",
          "notes": "",
          "meta": {
            "body_pct": 1.0,
            "wick_top_pct": 0.0,
            "wick_bottom_pct": 0.0,
            "entry_mode": "BODY_05",
            "role": "NEUTRAL",
            "bias_at_creation": "LONG",
            "has_bos": false,
            "bar_count": 5,
            "amplitude": 0.00030999999999981043,
            "quality": "WEAK"
          }
        },
        {
          "zone_type": "ORDER_BLOCK",
          "price_min": 1.15961,
          "price_max": 1.15965,
          "timeframe": "1m",
          "origin_time": "1970-01-01T00:29:24.349800",
          "direction": "SHORT",
          "role": "NEUTRAL",
          "strength": 3.0,
          "confidence": 0.6500000000006662,
          "components": [
            "orderblock",
            "leg_238_240"
          ],
          "zone_id": "ob_eurusd_1m_237_240",
          "entry_mode": "BODY_05",
          "quality": "WEAK",
          "reference_leg_id": "leg_238_240",
          "reference_event_id": null,
          "bias_at_creation": "LONG",
          "notes": "",
          "meta": {
            "body_pct": 0.8000000000026646,
            "wick_top_pct": 0.09999999999644729,
            "wick_bottom_pct": 0.10000000000088818,
            "entry_mode": "BODY_05",
            "role": "NEUTRAL",
            "bias_at_creation": "LONG",
            "has_bos": false,
            "bar_count": 3,
            "amplitude": 0.0003949999999999232,
            "quality": "WEAK"
          }
        },
        {
          "zone_type": "ORDER_BLOCK",
          "price_min": 1.159805,
          "price_max": 1.159825,
          "timeframe": "1m",
          "origin_time": "1970-01-01T00:29:24.349860",
          "direction": "LONG",
          "role": "NEUTRAL",
          "strength": 3.0,
          "confidence": 0.6500000000017764,
          "components": [
            "orderblock",
            "leg_240_247"
          ],
          "zone_id": "ob_eurusd_1m_238_247",
          "entry_mode": "BODY_05",
          "quality": "WEAK",
          "reference_leg_id": "leg_240_247",
          "reference_event_id": null,
          "bias_at_creation": "LONG",
          "notes": "",
          "meta": {
            "body_pct": 0.8000000000071055,
            "wick_top_pct": 0.19999999999289458,
            "wick_bottom_pct": 0.0,
            "entry_mode": "BODY_05",
            "role": "NEUTRAL",
            "bias_at_creation": "LONG",
            "has_bos": false,
            "bar_count": 8,
            "amplitude": 0.0004250000000001197,
            "quality": "WEAK"
          }
        },
        {
          "zone_type": "ORDER_BLOCK",
          "price_min": 1.159845,
          "price_max": 1.1598600000000001,
          "timeframe": "1m",
          "origin_time": "1970-01-01T00:29:24.350400",
          "direction": "LONG",
          "role": "NEUTRAL",
          "strength": 2.4390243902457214,
          "confidence": 0.7,
          "components": [
            "orderblock",
            "leg_247_248"
          ],
          "zone_id": "ob_eurusd_1m_247_248",
          "entry_mode": "BODY_05",
          "quality": "WEAK",
          "reference_leg_id": "leg_247_248",
          "reference_event_id": null,
          "bias_at_creation": "LONG",
          "notes": "",
          "meta": {
            "body_pct": 1.0,
            "wick_top_pct": 0.0,
            "wick_bottom_pct": 0.0,
            "entry_mode": "BODY_05",
            "role": "NEUTRAL",
            "bias_at_creation": "LONG",
            "has_bos": false,
            "bar_count": 2,
            "amplitude": 0.0002500000000000835,
            "quality": "WEAK"
          }
        },
        {
          "zone_type": "ORDER_BLOCK",
          "price_min": 1.15963,
          "price_max": 1.15971,
          "timeframe": "1m",
          "origin_time": "1970-01-01T00:29:24.350460",
          "direction": "LONG",
          "role": "NEUTRAL",
          "strength": 2.487804878048773,
          "confidence": 0.6404761904763415,
          "components": [
            "orderblock",
            "leg_248_251"
          ],
          "zone_id": "ob_eurusd_1m_248_251",
          "entry_mode": "BODY_05",
          "quality": "WEAK",
          "reference_leg_id": "leg_248_251",
          "reference_event_id": null,
          "bias_at_creation": "LONG",
          "notes": "",
          "meta": {
            "body_pct": 0.7619047619053662,
            "wick_top_pct": 0.04761904761934972,
            "wick_bottom_pct": 0.19047619047528416,
            "entry_mode": "BODY_05",
            "role": "NEUTRAL",
            "bias_at_creation": "LONG",
            "has_bos": false,
            "bar_count": 4,
            "amplitude": 0.0002549999999998942,
            "quality": "WEAK"
          }
        },
        {
          "zone_type": "ORDER_BLOCK",
          "price_min": 1.159845,
          "price_max": 1.159865,
          "timeframe": "1m",
          "origin_time": "1970-01-01T00:29:24.350640",
          "direction": "SHORT",
          "role": "NEUTRAL",
          "strength": 3.0,
          "confidence": 0.5750000000013877,
          "components": [
            "orderblock",
            "leg_251_258"
          ],
          "zone_id": "ob_eurusd_1m_251_258",
          "entry_mode": "WICK_TOUCH",
          "quality": "WEAK",
          "reference_leg_id": "leg_251_258",
          "reference_event_id": null,
          "bias_at_creation": "LONG",
          "notes": "",
          "meta": {
            "body_pct": 0.5000000000055511,
            "wick_top_pct": 0.24999999999167333,
            "wick_bottom_pct": 0.25000000000277556,
            "entry_mode": "WICK_TOUCH",
            "role": "NEUTRAL",
            "bias_at_creation": "LONG",
            "has_bos": false,
            "bar_count": 8,
            "amplitude": 0.0004750000000000032,
            "quality": "WEAK"
          }
        },
        {
          "zone_type": "ORDER_BLOCK",
          "price_min": 1.15963,
          "price_max": 1.1596549999999999,
          "timeframe": "1m",
          "origin_time": "1970-01-01T00:29:24.350880",
          "direction": "LONG",
          "role": "NEUTRAL",
          "strength": 3.0,
          "confidence": 0.7,
          "components": [
            "orderblock",
            "leg_258_268"
          ],
          "zone_id": "ob_eurusd_1m_255_268",
          "entry_mode": "BODY_05",
          "quality": "WEAK",
          "reference_leg_id": "leg_258_268",
          "reference_event_id": null,
          "bias_at_creation": "LONG",
          "notes": "",
          "meta": {
            "body_pct": 1.0,
            "wick_top_pct": 0.0,
            "wick_bottom_pct": 0.0,
            "entry_mode": "BODY_05",
            "role": "NEUTRAL",
            "bias_at_creation": "LONG",
            "has_bos": false,
            "bar_count": 11,
            "amplitude": 0.0003500000000000725,
            "quality": "WEAK"
          }
        },
        {
          "zone_type": "ORDER_BLOCK",
          "price_min": 1.15985,
          "price_max": 1.159865,
          "timeframe": "1m",
          "origin_time": "1970-01-01T00:29:24.351600",
          "direction": "LONG",
          "role": "NEUTRAL",
          "strength": 2.5853658536592086,
          "confidence": 0.5333333333345669,
          "components": [
            "orderblock",
            "leg_268_272"
          ],
          "zone_id": "ob_eurusd_1m_267_272",
          "entry_mode": "WICK_05",
          "quality": "WEAK",
          "reference_leg_id": "leg_268_272",
          "reference_event_id": null,
          "bias_at_creation": "LONG",
          "notes": "",
          "meta": {
            "body_pct": 0.33333333333826765,
            "wick_top_pct": 0.3333333333234647,
            "wick_bottom_pct": 0.33333333333826765,
            "entry_mode": "WICK_05",
            "role": "NEUTRAL",
            "bias_at_creation": "LONG",
            "has_bos": false,
            "bar_count": 5,
            "amplitude": 0.0002649999999999597,
            "quality": "WEAK"
          }
        },
        {
          "zone_type": "ORDER_BLOCK",
          "price_min": 1.15991,
          "price_max": 1.159915,
          "timeframe": "1m",
          "origin_time": "1970-01-01T00:29:24.351840",
          "direction": "LONG",
          "role": "NEUTRAL",
          "strength": 1.7073170731717884,
          "confidence": 0.7,
          "components": [
            "orderblock",
            "leg_272_279"
          ],
          "zone_id": "ob_eurusd_1m_271_279",
          "entry_mode": "BODY_05",
          "quality": "WEAK",
          "reference_leg_id": "leg_272_279",
          "reference_event_id": null,
          "bias_at_creation": "LONG",
          "notes": "",
          "meta": {
            "body_pct": 1.0,
            "wick_top_pct": 0.0,
            "wick_bottom_pct": 0.0,
            "entry_mode": "BODY_05",
            "role": "NEUTRAL",
            "bias_at_creation": "LONG",
            "has_bos": false,
            "bar_count": 8,
            "amplitude": 0.00017500000000003624,
            "quality": "WEAK"
          }
        },
        {
          "zone_type": "ORDER_BLOCK",
          "price_min": 1.15984,
          "price_max": 1.15989,
          "timeframe": "1m",
          "origin_time": "1970-01-01T00:29:24.352020",
          "direction": "LONG",
          "role": "NEUTRAL",
          "strength": 2.536585365856157,
          "confidence": 0.6772727272726355,
          "components": [
            "orderblock",
            "leg_279_284"
          ],
          "zone_id": "ob_eurusd_1m_274_284",
          "entry_mode": "BODY_05",
          "quality": "WEAK",
          "reference_leg_id": "leg_279_284",
          "reference_event_id": null,
          "bias_at_creation": "LONG",
          "notes": "",
          "meta": {
            "body_pct": 0.909090909090542,
            "wick_top_pct": 0.0,
            "wick_bottom_pct": 0.09090909090945792,
            "entry_mode": "BODY_05",
            "role": "NEUTRAL",
            "bias_at_creation": "LONG",
            "has_bos": false,
            "bar_count": 6,
            "amplitude": 0.000260000000000149,
            "quality": "WEAK"
          }
        },
        {
          "zone_type": "ORDER_BLOCK",
          "price_min": 1.16009,
          "price_max": 1.1601,
          "timeframe": "1m",
          "origin_time": "1970-01-01T00:29:24.352620",
          "direction": "LONG",
          "role": "NEUTRAL",
          "strength": 3.0,
          "confidence": 0.49166666666604986,
          "components": [
            "orderblock",
            "leg_284_286"
          ],
          "zone_id": "ob_eurusd_1m_284_286",
          "entry_mode": "BODY_TOUCH",
          "quality": "WEAK",
          "reference_leg_id": "leg_284_286",
          "reference_event_id": null,
          "bias_at_creation": "LONG",
          "notes": "",
          "meta": {
            "body_pct": 0.1666666666641995,
            "wick_top_pct": 0.8333333333358005,
            "wick_bottom_pct": 0.0,
            "entry_mode": "BODY_TOUCH",
            "role": "NEUTRAL",
            "bias_at_creation": "LONG",
            "has_bos": false,
            "bar_count": 3,
            "amplitude": 0.0003349999999999742,
            "quality": "WEAK"
          }
        }
      ],
      "active_zones": [],
      "poi_zones": [],
      "meta": {
        "zone_count": 57,
        "orderblocks_total": 57,
        "orderblocks_primary": 0,
        "orderblocks_countertrend": 0,
        "orderblocks_long": 36,
        "orderblocks_short": 21
      }
    }
  },
  "fxcm": {
    "market_state": "closed",
    "process_state": "idle",
    "lag_seconds": 114746.207924366,
    "last_bar_close_ms": 1764353579999,
    "last_bar_close_utc": "2025-11-28 18:12:59Z",
    "next_open_utc": "2025-11-30T22:15:00+00:00"
  }
}